LICENSE.txt
MANIFEST.in
README.md
setup.cfg
setup.py
schema2xl/__init__.py
schema2xl/schema2xl.py
schema2xl.egg-info/PKG-INFO
schema2xl.egg-info/SOURCES.txt
schema2xl.egg-info/dependency_links.txt
schema2xl.egg-info/requires.txt
schema2xl.egg-info/top_level.txt