Metadata-Version: 1.1
Name: schema2xl
Version: 0.0.1
Summary: DB schema to xlsx
Home-page: https://github.com/sohgett/schema2xl
Author: Toru Tanaka
Author-email: sohgett@gmail.com
License: MIT
Keywords: mysql excel
Platform: UNKNOWN
Classifier: Development Status :: 3 - Alpha
Classifier: License :: OSI Approved :: MIT License
Classifier: Programming Language :: Python :: 3
Classifier: Programming Language :: Python :: 3.6
Classifier: Programming Language :: Python :: 3.7
